WuyunZhishikuDisanBufenFix1/README.md
WuyunZhishikuDisanBufenFix1/__init__.py
WuyunZhishikuDisanBufenFix1/__main__.py
WuyunZhishikuDisanBufenFix1/file.epub
WuyunZhishikuDisanBufenFix1/index.html
WuyunZhishikuDisanBufenFix1/css/__init__.py
WuyunZhishikuDisanBufenFix1/css/annotations.css
WuyunZhishikuDisanBufenFix1/css/main.css
WuyunZhishikuDisanBufenFix1/css/normalize.css
WuyunZhishikuDisanBufenFix1/css/popup.css
WuyunZhishikuDisanBufenFix1/font/__init__.py
WuyunZhishikuDisanBufenFix1/font/fontello.eot
WuyunZhishikuDisanBufenFix1/font/fontello.svg
WuyunZhishikuDisanBufenFix1/font/fontello.ttf
WuyunZhishikuDisanBufenFix1/font/fontello.woff
WuyunZhishikuDisanBufenFix1/img/__init__.py
WuyunZhishikuDisanBufenFix1/img/annotator-glyph-sprite.png
WuyunZhishikuDisanBufenFix1/img/annotator-icon-sprite.png
WuyunZhishikuDisanBufenFix1/img/apple-touch-icon.png
WuyunZhishikuDisanBufenFix1/img/cancelfullscreen.png
WuyunZhishikuDisanBufenFix1/img/close.png
WuyunZhishikuDisanBufenFix1/img/fullscreen.png
WuyunZhishikuDisanBufenFix1/img/loader.gif
WuyunZhishikuDisanBufenFix1/img/menu-icon.png
WuyunZhishikuDisanBufenFix1/img/save.png
WuyunZhishikuDisanBufenFix1/img/saved.png
WuyunZhishikuDisanBufenFix1/img/settings-s.png
WuyunZhishikuDisanBufenFix1/img/settings.png
WuyunZhishikuDisanBufenFix1/img/star.png
WuyunZhishikuDisanBufenFix1/js/__init__.py
WuyunZhishikuDisanBufenFix1/js/epub.js
WuyunZhishikuDisanBufenFix1/js/epub.min.js
WuyunZhishikuDisanBufenFix1/js/epub.min.map
WuyunZhishikuDisanBufenFix1/js/hooks.min.js
WuyunZhishikuDisanBufenFix1/js/hooks.min.map
WuyunZhishikuDisanBufenFix1/js/reader.js
WuyunZhishikuDisanBufenFix1/js/reader.js.map
WuyunZhishikuDisanBufenFix1/js/reader.min.js
WuyunZhishikuDisanBufenFix1/js/reader.min.map
WuyunZhishikuDisanBufenFix1/js/hooks/__init__.py
WuyunZhishikuDisanBufenFix1/js/hooks/extensions/__init__.py
WuyunZhishikuDisanBufenFix1/js/hooks/extensions/highlight.js
WuyunZhishikuDisanBufenFix1/js/libs/__init__.py
wuyun_zhishiku_disan_bufen_fix1-2025.3.24.1.dist-info/METADATA
wuyun_zhishiku_disan_bufen_fix1-2025.3.24.1.dist-info/WHEEL
wuyun_zhishiku_disan_bufen_fix1-2025.3.24.1.dist-info/entry_points.txt
wuyun_zhishiku_disan_bufen_fix1-2025.3.24.1.dist-info/top_level.txt
wuyun_zhishiku_disan_bufen_fix1-2025.3.24.1.dist-info/RECORD
